open_crypto/__init__.py
open_crypto/_paths.py
open_crypto/examples.py
open_crypto/main.py
open_crypto/runner.py
open_crypto/validate.py
open_crypto/model/__init__.py
open_crypto/model/database/__init__.py
open_crypto/model/database/db_handler.py
open_crypto/model/database/tables.py
open_crypto/model/database/type_decorators.py
open_crypto/model/exchange/__init__.py
open_crypto/model/exchange/exchange.py
open_crypto/model/exchange/mapping.py
open_crypto/model/scheduling/__init__.py
open_crypto/model/scheduling/job.py
open_crypto/model/scheduling/scheduler.py
open_crypto/model/utilities/__init__.py
open_crypto/model/utilities/exceptions.py
open_crypto/model/utilities/export.py
open_crypto/model/utilities/github_downloader.py
open_crypto/model/utilities/kill_switch.py
open_crypto/model/utilities/loading_bar.py
open_crypto/model/utilities/patch_event_loop.py
open_crypto/model/utilities/settings.py
open_crypto/model/utilities/time_helper.py
open_crypto/model/utilities/utilities.py
open_crypto/model/validating/__init__.py
open_crypto/model/validating/api_map_validators.py
open_crypto/model/validating/base.py
open_crypto/model/validating/config_file_validator.py
open_crypto/model/validating/csv_export_template_validator.py
open_crypto/model/validating/errors.py
open_crypto/model/validating/program_config_validator.py
open_crypto/model/validating/request_template_validator.py
open_crypto/resources/__init__.py
open_crypto/resources/configs/__init__.py
open_crypto/resources/configs/global_config.py
open_crypto/resources/configs/program_config/config.yaml
open_crypto/resources/configs/user_configs/examples/example_export.yaml
open_crypto/resources/configs/user_configs/examples/exchange_listings.yaml
open_crypto/resources/configs/user_configs/examples/minute_candles.yaml
open_crypto/resources/configs/user_configs/examples/order_books.yaml
open_crypto/resources/configs/user_configs/examples/platform.yaml
open_crypto/resources/configs/user_configs/examples/static.yaml
open_crypto-3.9.9.1.dist-info/METADATA
open_crypto-3.9.9.1.dist-info/WHEEL
open_crypto-3.9.9.1.dist-info/top_level.txt
open_crypto-3.9.9.1.dist-info/RECORD
