Metadata-Version: 2.1
Name: open-crypto
Version: 3.9.9.1
Summary: UNKNOWN
Home-page: https://github.com/SteffenGue/open_crypto
Author: Steffen Guenther
Author-email: crypto@uni-bremen.de
License: UNKNOWN
Platform: UNKNOWN
Classifier: Programming Language :: Python :: 3
Classifier: License :: OSI Approved :: GNU Affero General Public License v3 or later (AGPLv3+)
Classifier: Operating System :: OS Independent
Requires-Python: >=3.8
Requires-Dist: aiohttp
Requires-Dist: aioschedule
Requires-Dist: certifi
Requires-Dist: datetime-periods
Requires-Dist: matplotlib
Requires-Dist: numpy (!=1.19.4)
Requires-Dist: oyaml
Requires-Dist: pandas
Requires-Dist: pytest
Requires-Dist: python-dateutil
Requires-Dist: sqlalchemy (>=1.4.22)
Requires-Dist: sqlalchemy-utils (>=0.37.8)
Requires-Dist: tqdm
Requires-Dist: validators
Requires-Dist: nest-asyncio
Requires-Dist: typeguard (>=2.12.1)
Requires-Dist: colorama
